ldap3/version.py
ldap3/__init__.py
ldap3/abstract/attrDef.py
ldap3/abstract/attribute.py
ldap3/abstract/entry.py
ldap3/abstract/objectDef.py
ldap3/abstract/operationalAttribute.py
ldap3/abstract/reader.py
ldap3/abstract/__init__.py
ldap3/compat/__init__.py
ldap3/core/connection.py
ldap3/core/exceptions.py
ldap3/core/pooling.py
ldap3/core/server.py
ldap3/core/timezone.py
ldap3/core/tls.py
ldap3/core/usage.py
ldap3/core/__init__.py
ldap3/extend/operation.py
ldap3/extend/__init__.py
ldap3/extend/microsoft/__init__.py
ldap3/extend/novell/getBindDn.py
ldap3/extend/novell/listReplicas.py
ldap3/extend/novell/nmasGetUniversalPassword.py
ldap3/extend/novell/nmasSetUniversalPassword.py
ldap3/extend/novell/partition_entry_count.py
ldap3/extend/novell/replicaInfo.py
ldap3/extend/novell/__init__.py
ldap3/extend/standard/modifyPassword.py
ldap3/extend/standard/PagedSearch.py
ldap3/extend/standard/whoAmI.py
ldap3/extend/standard/__init__.py
ldap3/operation/abandon.py
ldap3/operation/add.py
ldap3/operation/bind.py
ldap3/operation/compare.py
ldap3/operation/delete.py
ldap3/operation/extended.py
ldap3/operation/modify.py
ldap3/operation/modifyDn.py
ldap3/operation/search.py
ldap3/operation/unbind.py
ldap3/operation/__init__.py
ldap3/protocol/convert.py
ldap3/protocol/microsoft.py
ldap3/protocol/novell.py
ldap3/protocol/oid.py
ldap3/protocol/rfc2696.py
ldap3/protocol/rfc2849.py
ldap3/protocol/rfc3062.py
ldap3/protocol/rfc4511.py
ldap3/protocol/rfc4512.py
ldap3/protocol/__init__.py
ldap3/protocol/formatters/formatters.py
ldap3/protocol/formatters/standard.py
ldap3/protocol/formatters/__init__.py
ldap3/protocol/sasl/digestMd5.py
ldap3/protocol/sasl/external.py
ldap3/protocol/sasl/kerberos.py
ldap3/protocol/sasl/sasl.py
ldap3/protocol/sasl/__init__.py
ldap3/protocol/schemas/ad2012R2.py
ldap3/protocol/schemas/ds389.py
ldap3/protocol/schemas/edir888.py
ldap3/protocol/schemas/slapd24.py
ldap3/protocol/schemas/__init__.py
python3_ldap-0.9.8.4.dist-info/DESCRIPTION.rst
python3_ldap-0.9.8.4.dist-info/METADATA
python3_ldap-0.9.8.4.dist-info/metadata.json
python3_ldap-0.9.8.4.dist-info/RECORD
python3_ldap-0.9.8.4.dist-info/top_level.txt
python3_ldap-0.9.8.4.dist-info/WHEEL
