Metadata-Version: 1.1
Name: python3-ldap
Version: 0.9.8.4
Summary: A strictly RFC 4511 conforming LDAP V3 pure Python client. Same codebase for Python 2, Python3, PyPy and PyPy 3
Home-page: https://github.com/cannatag/ldap3
Author: Giovanni Cannata
Author-email: cannatag@gmail.com
License: LGPL v3
Keywords: python3 python2 ldap
Platform: UNKNOWN
Classifier: Development Status :: 4 - Beta
Classifier: Intended Audience :: Developers
Classifier: Intended Audience :: System Administrators
Classifier: Operating System :: MacOS :: MacOS X
Classifier: Operating System :: Microsoft :: Windows
Classifier: Operating System :: POSIX :: Linux
Classifier: License :: OSI Approved :: GNU Lesser General Public License v3 (LGPLv3)
Classifier: Programming Language :: Python
Classifier: Programming Language :: Python :: 2
Classifier: Programming Language :: Python :: 3
Classifier: Topic :: Software Development :: Libraries :: Python Modules
Classifier: Topic :: System :: Systems Administration :: Authentication/Directory :: LDAP
